histastro/__init__.py
histastro/constants.py
histastro/coordinates.py
histastro/datetime.py
histastro/moon.py
histastro/planets.py
histastro/plot.py
histastro-0.0.8.dist-info/licenses/LICENCE
histastro-0.0.8.dist-info/METADATA
histastro-0.0.8.dist-info/WHEEL
histastro-0.0.8.dist-info/top_level.txt
histastro-0.0.8.dist-info/RECORD
