Metadata-Version: 2.4
Name: histastro
Version: 0.0.8
Summary: A Python package for historical-astronomy calculations of Sun, Moon and planets
Author-email: Marc van der Sluys <git@vandersluys.nl>
License-Expression: GPL-3.0-or-later
Project-URL: GitHub, https://github.com/MarcvdSluys/HistAstro
Project-URL: ReadTheDocs, https://histastro.readthedocs.io
Project-URL: Homepage, https://astro.ru.nl/~sluys/HistAstro
Keywords: astronomy,history,ephemeris,sun,moon,planets
Classifier: Development Status :: 4 - Beta
Classifier: Intended Audience :: Developers
Classifier: Intended Audience :: Education
Classifier: Intended Audience :: Science/Research
Classifier: Natural Language :: English
Classifier: Operating System :: OS Independent
Classifier: Programming Language :: Python :: 3
Classifier: Topic :: Scientific/Engineering :: Astronomy
Classifier: Topic :: Sociology :: History
License-File: LICENCE
Requires-Dist: fortranformat
Requires-Dist: numpy
Dynamic: license-file
